amqp_fabric/__init__.py
amqp_fabric/abstract_service_api.py
amqp_fabric/amq_broker_connector.py
amqp_fabric/logging_amqp_handler.py
amqp_fabric-0.2.3.dist-info/licenses/AUTHORS.md
amqp_fabric-0.2.3.dist-info/licenses/LICENSE.txt
amqp_fabric-0.2.3.dist-info/METADATA
amqp_fabric-0.2.3.dist-info/WHEEL
amqp_fabric-0.2.3.dist-info/top_level.txt
amqp_fabric-0.2.3.dist-info/RECORD
