Metadata-Version: 2.4
Name: amqp-fabric
Version: 0.2.3
Summary: AMQP Fabric is an AMQP based microservice orchestration and communication framework
Home-page: https://github.com/imubit/amqp-fabric/
Author: Meir Tseitlin
License: LGPLv3
Project-URL: Documentation, https://github.com/imubit/amqp-fabric/
Platform: any
Classifier: Development Status :: 4 - Beta
Classifier: Programming Language :: Python
Requires-Python: >=3.8
License-File: LICENSE.txt
License-File: AUTHORS.md
Requires-Dist: importlib-metadata; python_version < "3.8"
Requires-Dist: aio-pika>=9.3.0
Requires-Dist: apscheduler
Requires-Dist: cachetools
Provides-Extra: testing
Requires-Dist: pytest; extra == "testing"
Requires-Dist: pytest-cov; extra == "testing"
Requires-Dist: pytest-asyncio; extra == "testing"
Dynamic: license-file
